nbu_privat_currency_sale/__init__.py
nbu_privat_currency_sale/currency_actions.py
nbu_privat_currency_sale-0.0.1.dist-info/LICENSE
nbu_privat_currency_sale-0.0.1.dist-info/METADATA
nbu_privat_currency_sale-0.0.1.dist-info/WHEEL
nbu_privat_currency_sale-0.0.1.dist-info/top_level.txt
nbu_privat_currency_sale-0.0.1.dist-info/RECORD
