Metadata-Version: 2.1
Name: nbu-privat-currency-sale
Version: 0.0.1
Summary: A library for getting currency sale rates of National Bank of Ukraine and PrivatBank, compare it graphically by currency selection during preset date range.
Author: Nazar Khort
Author-email: nazar.khort@gmail.com
License: MIT
Project-URL: Source, https://github.com/0brain/nbu_privat_currency_sale
Keywords: python,exchange rate,privatbank,NBU,currency sale,National Bank of Ukraine,compare currency,course change chart,exchange rate chart,banks exchange rate,compare banks exchange rate
Platform: UNKNOWN
Classifier: Intended Audience :: Education
Classifier: Programming Language :: Python :: 3
Classifier: License :: OSI Approved :: MIT License
Classifier: Operating System :: OS Independent
License-File: LICENSE
Requires-Dist: requests (==2.27.1)
Requires-Dist: matplotlib (==3.5.1)
